bytehub/__init__.py
bytehub/_base.py
bytehub/_connection.py
bytehub/_model.py
bytehub/_timeseries.py
bytehub/_upgrade.py
bytehub/_utils.py
bytehub/_version.py
bytehub/cloud.py
bytehub/core.py
bytehub/exceptions.py
bytehub/_storage/__init__.py
bytehub/_storage/_base.py
bytehub/_storage/dask.py
bytehub/_storage/pandas.py
bytehub-0.4.0.dist-info/LICENSE
bytehub-0.4.0.dist-info/METADATA
bytehub-0.4.0.dist-info/WHEEL
bytehub-0.4.0.dist-info/top_level.txt
bytehub-0.4.0.dist-info/RECORD
