Metadata-Version: 2.1
Name: bytehub
Version: 0.4.0
Summary: ByteHub Timeseries Feature Store
Home-page: https://bytehub.ai
Author: ByteHub AI Limited
License: UNKNOWN
Platform: UNKNOWN
Requires-Dist: pandas (>=1.1)
Requires-Dist: pyarrow (>=3.0)
Requires-Dist: dask[dataframe,delayed] (>=2021)
Requires-Dist: cloudpickle (>=1.3.0)
Requires-Dist: SQLAlchemy (>=1.3)
Requires-Dist: alembic (>=1.5)
Requires-Dist: requests (>=2)
Requires-Dist: requests-oauthlib (>=1.1)
Provides-Extra: aws
Requires-Dist: s3fs (==0.4) ; extra == 'aws'
Provides-Extra: azure
Requires-Dist: adlfs (>=0.6) ; extra == 'azure'
Provides-Extra: cloud
Requires-Dist: s3fs (==0.4) ; extra == 'cloud'
Provides-Extra: dev
Requires-Dist: pytest ; extra == 'dev'
Requires-Dist: black ; extra == 'dev'
Requires-Dist: bump2version ; extra == 'dev'
Requires-Dist: jupyterlab ; extra == 'dev'
Requires-Dist: pre-commit ; extra == 'dev'
Requires-Dist: pdoc3 ; extra == 'dev'
Provides-Extra: gcp
Requires-Dist: gcsfs (==0.8) ; extra == 'gcp'
